MANIFEST.in
add.png
setup.py
todos.txt
todo_webapp/__init__.py
todo_webapp/functions.py
todo_webapp/main.py
todo_webapp/todo-list-CLI.py
todo_webapp/todo-list-GUI.py
todo_webapp.egg-info/PKG-INFO
todo_webapp.egg-info/SOURCES.txt
todo_webapp.egg-info/dependency_links.txt
todo_webapp.egg-info/requires.txt
todo_webapp.egg-info/top_level.txt